[
  {
    "id": "14337701552396ff",
    "title": "Тарпищев словами «он вернулся» оценил игру Медведева",
    "sport": "Теннис",
    "category": "Теннис",
    "imageUrl": "/images/news-placeholder.jpg",
    "teaser": "Тарпищев словами «он вернулся» оценил игру Медведева",
    "fullContent": "",
    "sourceName": "РБК Спорт",
    "sourceUrl": "https://sportrbc.ru/news/69b80f5f9a7947aac94c7259",
    "publishedAt": "2026-03-16T14:54:22.000Z",
    "createdAt": "2026-03-16T15:06:32.405Z",
    "updatedAt": "2026-03-16T15:06:32.405Z"
  },
  {
    "id": "9294cd7f542a9830",
    "title": "«Челси» оштрафовали на £10,75 млн за финансовые нарушения",
    "sport": "Футбол",
    "category": "Футбол",
    "imageUrl": "https://s0.rbk.ru/v6_top_pics/media/img/3/91/347736706618913.jpeg",
    "teaser": "«Челси» оштрафовали на £10,75 млн за финансовые нарушения",
    "fullContent": "",
    "sourceName": "РБК Спорт",
    "sourceUrl": "https://sportrbc.ru/news/69b8071c9a7947f0e394e00f",
    "publishedAt": "2026-03-16T14:26:50.000Z",
    "createdAt": "2026-03-16T15:06:35.471Z",
    "updatedAt": "2026-03-16T15:06:35.471Z"
  },
  {
    "id": "f07de10595daa8ed",
    "title": "Ирландский боец UFC заявил, что не верит в травму Махачева",
    "sport": "Единоборства",
    "category": "Единоборства",
    "imageUrl": "https://s0.rbk.ru/v6_top_pics/media/img/5/78/347736688665785.jpeg",
    "teaser": "Ирландский боец UFC заявил, что не верит в травму Махачева",
    "fullContent": "",
    "sourceName": "РБК Спорт",
    "sourceUrl": "https://sportrbc.ru/news/69b805809a7947586334c585",
    "publishedAt": "2026-03-16T14:01:29.000Z",
    "createdAt": "2026-03-16T15:06:33.422Z",
    "updatedAt": "2026-03-16T15:06:33.422Z"
  },
  {
    "id": "f8bf3ac8404ebea5",
    "title": "Обвиняемому в убийстве женщины футболисту не будут платить зарплату",
    "sport": "Футбол",
    "category": "Футбол",
    "imageUrl": "https://s0.rbk.ru/v6_top_pics/media/img/1/97/347736644402971.jpeg",
    "teaser": "Обвиняемому в убийстве женщины футболисту не будут платить зарплату",
    "fullContent": "",
    "sourceName": "РБК Спорт",
    "sourceUrl": "https://sportrbc.ru/news/69b7f2b89a7947361cd1a8df",
    "publishedAt": "2026-03-16T13:57:00.000Z",
    "createdAt": "2026-03-16T15:06:36.369Z",
    "updatedAt": "2026-03-16T15:06:36.369Z"
  },
  {
    "id": "ae4b7edc0de36469",
    "title": "Россиянин возглавил рейтинг лучших молодых полузащитников не из топ-5 лиг",
    "sport": "Футбол",
    "category": "Футбол",
    "imageUrl": "https://s0.rbk.ru/v6_top_pics/media/img/8/68/347736668127688.png",
    "teaser": "Россиянин возглавил рейтинг лучших молодых полузащитников не из топ-5 лиг",
    "fullContent": "",
    "sourceName": "РБК Спорт",
    "sourceUrl": "https://sportrbc.ru/news/69b7fe7c9a794712440e7e68",
    "publishedAt": "2026-03-16T13:28:11.000Z",
    "createdAt": "2026-03-16T15:06:37.612Z",
    "updatedAt": "2026-03-16T15:06:37.612Z"
  },
  {
    "id": "3874e48302116f64",
    "title": "КДК РФС рассмотрит поведение тренеров Челестини и Талалаева в матче РПЛ",
    "sport": "Футбол",
    "category": "Футбол",
    "imageUrl": "https://s0.rbk.ru/v6_top_pics/media/img/3/92/347736660166923.jpeg",
    "teaser": "КДК РФС рассмотрит поведение тренеров Челестини и Талалаева в матче РПЛ",
    "fullContent": "",
    "sourceName": "РБК Спорт",
    "sourceUrl": "https://sportrbc.ru/news/69b7fb1d9a794715ff001613",
    "publishedAt": "2026-03-16T13:13:24.000Z",
    "createdAt": "2026-03-16T15:06:39.649Z",
    "updatedAt": "2026-03-16T15:06:39.649Z"
  },
  {
    "id": "573127a208d2e4e6",
    "title": "Аутсайдер Первой лиги расторг контракт с черногорским тренером",
    "sport": "Футбол",
    "category": "Футбол",
    "imageUrl": "https://s0.rbk.ru/v6_top_pics/media/img/9/96/347736647862969.png",
    "teaser": "Аутсайдер Первой лиги расторг контракт с черногорским тренером",
    "fullContent": "",
    "sourceName": "РБК Спорт",
    "sourceUrl": "https://sportrbc.ru/news/69b7f71a9a79471975c916a5",
    "publishedAt": "2026-03-16T12:53:09.000Z",
    "createdAt": "2026-03-16T15:06:41.936Z",
    "updatedAt": "2026-03-16T15:06:41.936Z"
  },
  {
    "id": "bf5eae808e3156f7",
    "title": "Плющенко призвал Тутберидзе не обещать его фигуристам «места в сборной»",
    "sport": "Другое",
    "category": "Фигурное катание",
    "imageUrl": "https://s0.rbk.ru/v6_top_pics/media/img/3/79/347736630372793.jpeg",
    "teaser": "Плющенко призвал Тутберидзе не обещать его фигуристам «места в сборной»",
    "fullContent": "",
    "sourceName": "РБК Спорт",
    "sourceUrl": "https://sportrbc.ru/news/69b7f1749a794798ed4d9d2a",
    "publishedAt": "2026-03-16T12:51:38.000Z",
    "createdAt": "2026-03-16T15:06:38.631Z",
    "updatedAt": "2026-03-16T15:06:38.631Z"
  },
  {
    "id": "006b5aff0945224c",
    "title": "РПЛ назвала даты столичных дерби и матчей лидеров",
    "sport": "Футбол",
    "category": "Футбол",
    "imageUrl": "https://s0.rbk.ru/v6_top_pics/media/img/2/22/347736609648222.png",
    "teaser": "РПЛ назвала даты столичных дерби и матчей лидеров",
    "fullContent": "",
    "sourceName": "РБК Спорт",
    "sourceUrl": "https://sportrbc.ru/news/69b7e7639a794773d844e710",
    "publishedAt": "2026-03-16T12:16:09.000Z",
    "createdAt": "2026-03-16T15:06:40.922Z",
    "updatedAt": "2026-03-16T15:06:40.922Z"
  },
  {
    "id": "d02ca69280ac28ba",
    "title": "РБК представил рейтинг букмекеров 2026 года",
    "sport": "Другое",
    "category": "Другие",
    "imageUrl": "https://s0.rbk.ru/v6_top_pics/media/img/4/24/347736471042244.jpeg",
    "teaser": "РБК представил рейтинг букмекеров 2026 года",
    "fullContent": "",
    "sourceName": "РБК Спорт",
    "sourceUrl": "https://sportrbc.ru/news/69b7b1e39a794732bb7fa5bc",
    "publishedAt": "2026-03-16T08:45:51.000Z",
    "createdAt": "2026-03-16T15:06:34.445Z",
    "updatedAt": "2026-03-16T15:06:34.445Z"
  }
]