[
  {
    "id": "1f4eec5c4b720a97",
    "title": "Российским триатлонистам вернули право выступать на турнирах Ironman",
    "sport": "Другое",
    "category": "Другие",
    "imageUrl": "https://s0.rbk.ru/v6_top_pics/media/img/3/85/347837696277853.jpeg",
    "teaser": "Российским триатлонистам вернули право выступать на турнирах Ironman",
    "fullContent": "",
    "sourceName": "РБК Спорт",
    "sourceUrl": "https://sportrbc.ru/news/6a4bb5019a79474600cabca0",
    "publishedAt": "2026-07-11T11:43:24.000Z",
    "createdAt": "2026-07-11T11:55:37.381Z",
    "updatedAt": "2026-07-11T11:55:37.381Z"
  },
  {
    "id": "09b3fbe978977f46",
    "title": "Вылетевший из РПЛ «Нижний Новгород» сообщил о переименовании клуба",
    "sport": "Футбол",
    "category": "Футбол",
    "imageUrl": "https://s0.rbk.ru/v6_top_pics/media/img/8/27/347837683488278.jpeg",
    "teaser": "Вылетевший из РПЛ «Нижний Новгород» сообщил о переименовании клуба",
    "fullContent": "",
    "sourceName": "РБК Спорт",
    "sourceUrl": "https://sportrbc.ru/news/6a4beea79a7947da15f81b8d",
    "publishedAt": "2026-07-11T11:23:35.000Z",
    "createdAt": "2026-07-11T11:55:38.252Z",
    "updatedAt": "2026-07-11T11:55:38.252Z"
  },
  {
    "id": "667f553cd0c8acf3",
    "title": "Билеты на матч 1/4 финала ЧМ‑2026 Англия — Норвегия перепродают за $1 млн",
    "sport": "Футбол",
    "category": "Футбол",
    "imageUrl": "https://s0.rbk.ru/v6_top_pics/media/img/4/93/347837672989934.jpeg",
    "teaser": "Билеты на матч 1/4 финала ЧМ‑2026 Англия — Норвегия перепродают за $1 млн",
    "fullContent": "",
    "sourceName": "РБК Спорт",
    "sourceUrl": "https://sportrbc.ru/news/6a4d2efc9a7947f844f9d4d3",
    "publishedAt": "2026-07-11T11:02:14.000Z",
    "createdAt": "2026-07-11T11:55:39.270Z",
    "updatedAt": "2026-07-11T11:55:39.270Z"
  },
  {
    "id": "0490cd590fd0b1bf",
    "title": "Обладатель Кубка Гагарина Блажиевский перешел в «Динамо»",
    "sport": "Хоккей",
    "category": "Хоккей",
    "imageUrl": "https://s0.rbk.ru/v6_top_pics/media/img/4/60/347837651260604.jpeg",
    "teaser": "Обладатель Кубка Гагарина Блажиевский перешел в «Динамо»",
    "fullContent": "",
    "sourceName": "РБК Спорт",
    "sourceUrl": "https://sportrbc.ru/news/6a4d3b629a7947c430ee3362",
    "publishedAt": "2026-07-11T10:23:28.000Z",
    "createdAt": "2026-07-11T11:55:40.289Z",
    "updatedAt": "2026-07-11T11:55:40.289Z"
  },
  {
    "id": "9e9680d4a7d350e8",
    "title": "Какие футболисты входят в список лучших бомбардиров на ЧМ-2026",
    "sport": "Футбол",
    "category": "Футбол",
    "imageUrl": "https://s0.rbk.ru/v6_top_pics/media/img/3/83/347837104201833.jpeg",
    "teaser": "Какие футболисты входят в список лучших бомбардиров на ЧМ-2026",
    "fullContent": "",
    "sourceName": "РБК Спорт",
    "sourceUrl": "https://sportrbc.ru/news/6a51363f9a79471011148b4f",
    "publishedAt": "2026-07-11T09:31:15.000Z",
    "createdAt": "2026-07-11T11:55:43.406Z",
    "updatedAt": "2026-07-11T11:55:43.406Z"
  },
  {
    "id": "68b1c4999526523b",
    "title": "Украинская биатлонистка объяснила свой переезд в Россию",
    "sport": "Другое",
    "category": "Биатлон",
    "imageUrl": "https://s0.rbk.ru/v6_top_pics/media/img/4/29/347837597216294.jpeg",
    "teaser": "Украинская биатлонистка объяснила свой переезд в Россию",
    "fullContent": "",
    "sourceName": "РБК Спорт",
    "sourceUrl": "https://sportrbc.ru/news/6a4d6db79a7947e65d0e62c4",
    "publishedAt": "2026-07-11T09:02:01.000Z",
    "createdAt": "2026-07-11T11:55:41.359Z",
    "updatedAt": "2026-07-11T11:55:41.359Z"
  },
  {
    "id": "48ed8bfd47d1b4b4",
    "title": "Рэпер Дрейк поставил $1 млн на победу Макгрегора в первом бою за пять лет",
    "sport": "Единоборства",
    "category": "Единоборства",
    "imageUrl": "https://s0.rbk.ru/v6_top_pics/media/img/2/20/347837570338202.jpeg",
    "teaser": "Рэпер Дрейк поставил $1 млн на победу Макгрегора в первом бою за пять лет",
    "fullContent": "",
    "sourceName": "РБК Спорт",
    "sourceUrl": "https://sportrbc.ru/news/6a4ff73c9a7947831b2a8b3a",
    "publishedAt": "2026-07-11T08:12:04.000Z",
    "createdAt": "2026-07-11T11:55:42.417Z",
    "updatedAt": "2026-07-11T11:55:42.417Z"
  },
  {
    "id": "7cfb8c0a21d14310",
    "title": "Мужчина с гаечным ключом проник в пресс-центр сборной Англии на ЧМ-2026",
    "sport": "Футбол",
    "category": "Футбол",
    "imageUrl": "https://s0.rbk.ru/v6_top_pics/media/img/4/66/347837558081664.jpeg",
    "teaser": "Мужчина с гаечным ключом проник в пресс-центр сборной Англии на ЧМ-2026",
    "fullContent": "",
    "sourceName": "РБК Спорт",
    "sourceUrl": "https://sportrbc.ru/news/6a4feb999a794705a53110e1",
    "publishedAt": "2026-07-11T07:57:04.000Z",
    "createdAt": "2026-07-11T11:55:46.759Z",
    "updatedAt": "2026-07-11T11:55:46.759Z"
  },
  {
    "id": "8eab14f718d38a9b",
    "title": "Один из лучших игроков НБА подписал новый контракт с «Сан-Антонио»",
    "sport": "Баскетбол",
    "category": "Баскетбол",
    "imageUrl": "https://s0.rbk.ru/v6_top_pics/media/img/7/01/347837549828017.jpeg",
    "teaser": "Один из лучших игроков НБА подписал новый контракт с «Сан-Антонио»",
    "fullContent": "",
    "sourceName": "РБК Спорт",
    "sourceUrl": "https://sportrbc.ru/news/6a4d57649a79475d3448b452",
    "publishedAt": "2026-07-11T07:40:28.000Z",
    "createdAt": "2026-07-11T11:55:45.554Z",
    "updatedAt": "2026-07-11T11:55:45.554Z"
  },
  {
    "id": "e65097578695cb95",
    "title": "Заболевший лидер сборной Англии сможет сыграть в матче 1/4 финала ЧМ-2026",
    "sport": "Футбол",
    "category": "Футбол",
    "imageUrl": "https://s0.rbk.ru/v6_top_pics/media/img/4/75/347837542080754.jpeg",
    "teaser": "Заболевший лидер сборной Англии сможет сыграть в матче 1/4 финала ЧМ-2026",
    "fullContent": "",
    "sourceName": "РБК Спорт",
    "sourceUrl": "https://sportrbc.ru/news/6a5137b89a79478f6cfec458",
    "publishedAt": "2026-07-11T07:26:48.000Z",
    "createdAt": "2026-07-11T11:55:44.457Z",
    "updatedAt": "2026-07-11T11:55:44.457Z"
  }
]