[
  {
    "id": "2e978df4b0d0381a",
    "title": "Макгрегор рассказал, когда вернется в UFC после тяжелой травмы колена",
    "sport": "Единоборства",
    "category": "Единоборства",
    "imageUrl": "https://s0.rbk.ru/v6_top_pics/media/img/1/55/347844748726551.jpeg",
    "teaser": "Макгрегор рассказал, когда вернется в UFC после тяжелой травмы колена",
    "fullContent": "",
    "sourceName": "РБК Спорт",
    "sourceUrl": "https://sportrbc.ru/news/6a395ddb9a7947295c58b8fe",
    "publishedAt": "2026-07-19T22:00:00.000Z",
    "createdAt": "2026-07-19T17:03:12.690Z",
    "updatedAt": "2026-07-19T17:03:12.690Z"
  },
  {
    "id": "607a824cc9b518f9",
    "title": "Двукратный победитель «Тур де Франс» снялся с многодневки после падения",
    "sport": "Другое",
    "category": "Другие",
    "imageUrl": "https://s0.rbk.ru/v6_top_pics/media/img/3/63/347844794019633.jpeg",
    "teaser": "Двукратный победитель «Тур де Франс» снялся с многодневки после падения",
    "fullContent": "",
    "sourceName": "РБК Спорт",
    "sourceUrl": "https://sportrbc.ru/news/6a4cfdca9a79472caa8a5860",
    "publishedAt": "2026-07-19T22:00:00.000Z",
    "createdAt": "2026-07-19T17:03:12.698Z",
    "updatedAt": "2026-07-19T17:03:12.698Z"
  },
  {
    "id": "1592b1db51b8c1af",
    "title": "Как главный судья финала ЧМ едва не оказался в тюрьме",
    "sport": "Другое",
    "category": "ЧМ-2026",
    "imageUrl": "https://s0.rbk.ru/v6_top_pics/media/img/1/65/347843952151651.jpeg",
    "teaser": "Как главный судья финала ЧМ едва не оказался в тюрьме",
    "fullContent": "",
    "sourceName": "РБК Спорт",
    "sourceUrl": "https://sportrbc.ru/news/6a5bb0ae9a7947954301e361",
    "publishedAt": "2026-07-19T22:00:00.000Z",
    "createdAt": "2026-07-19T17:03:12.704Z",
    "updatedAt": "2026-07-19T17:03:12.704Z"
  },
  {
    "id": "72c7aa2bd45cea42",
    "title": "Испания — Аргентина. Онлайн финала ЧМ-2026 -:- Испания Не начался Аргентина",
    "sport": "Другое",
    "category": "Общее",
    "imageUrl": "https://s0.rbk.ru/v6_top_pics/media/img/2/82/347844585366822.png",
    "teaser": "Испания — Аргентина. Онлайн финала ЧМ-2026 -:- Испания Не начался Аргентина",
    "fullContent": "",
    "sourceName": "РБК Спорт",
    "sourceUrl": "https://sportrbc.ru/news/6a5cad1c9a79475a694f068f",
    "publishedAt": "2026-07-19T22:00:00.000Z",
    "createdAt": "2026-07-19T17:03:13.992Z",
    "updatedAt": "2026-07-19T17:03:13.992Z"
  },
  {
    "id": "448b7b7f19e9d704",
    "title": "Американская боксерша и экс-претендент на титул WBC погибла в ДТП",
    "sport": "Единоборства",
    "category": "Единоборства",
    "imageUrl": "https://s0.rbk.ru/v6_top_pics/media/img/4/16/347844728471164.jpeg",
    "teaser": "Американская боксерша и экс-претендент на титул WBC погибла в ДТП",
    "fullContent": "",
    "sourceName": "РБК Спорт",
    "sourceUrl": "https://sportrbc.ru/news/6a537bdd9a794727484991de",
    "publishedAt": "2026-07-19T22:00:00.000Z",
    "createdAt": "2026-07-19T17:03:13.998Z",
    "updatedAt": "2026-07-19T17:03:13.998Z"
  },
  {
    "id": "bff55a0e9281dc41",
    "title": "Рублев связал с везением свою победу на турнире в Швеции",
    "sport": "Теннис",
    "category": "Теннис",
    "imageUrl": "https://s0.rbk.ru/v6_top_pics/media/img/4/64/347844729388644.jpeg",
    "teaser": "Рублев связал с везением свою победу на турнире в Швеции",
    "fullContent": "",
    "sourceName": "РБК Спорт",
    "sourceUrl": "https://sportrbc.ru/news/6a5ce0c09a79476d5ff38ecd",
    "publishedAt": "2026-07-19T22:00:00.000Z",
    "createdAt": "2026-07-19T17:03:14.003Z",
    "updatedAt": "2026-07-19T17:03:14.003Z"
  },
  {
    "id": "1d6546dcd63bcf56",
    "title": "19-летний пилот Mercedes выиграл шестую в сезоне гонку «Формулы-1»",
    "sport": "Другое",
    "category": "Формула-1",
    "imageUrl": "https://s0.rbk.ru/v6_top_pics/media/img/1/73/347844710665731.jpeg",
    "teaser": "19-летний пилот Mercedes выиграл шестую в сезоне гонку «Формулы-1»",
    "fullContent": "",
    "sourceName": "РБК Спорт",
    "sourceUrl": "https://sportrbc.ru/news/6a5cdbeb9a794728caf527f0",
    "publishedAt": "2026-07-19T22:00:00.000Z",
    "createdAt": "2026-07-19T17:03:14.008Z",
    "updatedAt": "2026-07-19T17:03:14.008Z"
  },
  {
    "id": "9ea0a8004b64f6c3",
    "title": "Футболист Рабьо назвал «позорной» игру Франции в матче за бронзу ЧМ",
    "sport": "Футбол",
    "category": "Футбол",
    "imageUrl": "https://s0.rbk.ru/v6_top_pics/media/img/5/70/347844700997705.jpeg",
    "teaser": "Футболист Рабьо назвал «позорной» игру Франции в матче за бронзу ЧМ",
    "fullContent": "",
    "sourceName": "РБК Спорт",
    "sourceUrl": "https://sportrbc.ru/news/6a5cd4729a794747182248fb",
    "publishedAt": "2026-07-19T22:00:00.000Z",
    "createdAt": "2026-07-19T17:03:14.016Z",
    "updatedAt": "2026-07-19T17:03:14.016Z"
  },
  {
    "id": "e200ada21ff04b1e",
    "title": "Рублев завоевал первый титул ATP с февраля 2025 года",
    "sport": "Теннис",
    "category": "Теннис",
    "imageUrl": "https://s0.rbk.ru/v6_top_pics/media/img/6/38/347844660767386.jpeg",
    "teaser": "Рублев завоевал первый титул ATP с февраля 2025 года",
    "fullContent": "",
    "sourceName": "РБК Спорт",
    "sourceUrl": "https://sportrbc.ru/news/6a2bc5c49a794739007497d6",
    "publishedAt": "2026-07-19T22:00:00.000Z",
    "createdAt": "2026-07-19T17:03:14.021Z",
    "updatedAt": "2026-07-19T17:03:14.021Z"
  },
  {
    "id": "411862abc395e34e",
    "title": "Месси обратился к своим партнерам по сборной перед финалом ЧМ-2026",
    "sport": "Футбол",
    "category": "Футбол",
    "imageUrl": "https://s0.rbk.ru/v6_top_pics/media/img/4/68/347844645978684.jpeg",
    "teaser": "Месси обратился к своим партнерам по сборной перед финалом ЧМ-2026",
    "fullContent": "",
    "sourceName": "РБК Спорт",
    "sourceUrl": "https://sportrbc.ru/news/6a1747b19a79473b2caeb190",
    "publishedAt": "2026-07-19T22:00:00.000Z",
    "createdAt": "2026-07-19T17:03:14.026Z",
    "updatedAt": "2026-07-19T17:03:14.026Z"
  }
]