[
  {
    "id": "b35efc0b21b7ad17",
    "title": "Медведев вышел в полуфинал «Мастерс» в Индиан-Уэллсе, обыграв чемпиона",
    "sport": "Теннис",
    "category": "Теннис",
    "imageUrl": "https://s0.rbk.ru/v6_top_pics/media/img/4/46/347733268910464.jpeg",
    "teaser": "Медведев вышел в полуфинал «Мастерс» в Индиан-Уэллсе, обыграв чемпиона",
    "fullContent": "",
    "sourceName": "РБК Спорт",
    "sourceUrl": "https://sportrbc.ru/news/69b2d08a9a7947872e06ee71",
    "publishedAt": "2026-03-13T02:16:32.000Z",
    "createdAt": "2026-03-13T07:02:27.820Z",
    "updatedAt": "2026-03-13T07:02:27.820Z"
  },
  {
    "id": "a4bca88683f08f99",
    "title": "Дюплантис в 15-й раз побил мировой рекорд в прыжках с шестом",
    "sport": "Другое",
    "category": "Другие",
    "imageUrl": "https://s0.rbk.ru/v6_top_pics/media/img/8/41/347733475000418.jpeg",
    "teaser": "Дюплантис в 15-й раз побил мировой рекорд в прыжках с шестом",
    "fullContent": "",
    "sourceName": "РБК Спорт",
    "sourceUrl": "https://sportrbc.ru/news/69b320c49a79472d5d8da5f1",
    "publishedAt": "2026-03-12T20:57:20.000Z",
    "createdAt": "2026-03-13T07:02:28.910Z",
    "updatedAt": "2026-03-13T07:02:28.910Z"
  },
  {
    "id": "3cae5d38792da151",
    "title": "Первая ракетка мира Соболенко вышла в полуфинал турнира в Индиан-Уэллсе",
    "sport": "Теннис",
    "category": "Теннис",
    "imageUrl": "https://s0.rbk.ru/v6_top_pics/media/img/7/41/347733428773417.jpeg",
    "teaser": "Первая ракетка мира Соболенко вышла в полуфинал турнира в Индиан-Уэллсе",
    "fullContent": "",
    "sourceName": "РБК Спорт",
    "sourceUrl": "https://sportrbc.ru/news/69b3104d9a794760a032419d",
    "publishedAt": "2026-03-12T20:18:36.000Z",
    "createdAt": "2026-03-13T07:02:30.009Z",
    "updatedAt": "2026-03-13T07:02:30.009Z"
  },
  {
    "id": "e655b0b7505b2793",
    "title": "Мишин заявил, что Валиева нужна российскому фигурному катанию как воздух",
    "sport": "Другое",
    "category": "Фигурное катание",
    "imageUrl": "https://s0.rbk.ru/v6_top_pics/media/img/0/30/347733449206300.jpeg",
    "teaser": "Мишин заявил, что Валиева нужна российскому фигурному катанию как воздух",
    "fullContent": "",
    "sourceName": "РБК Спорт",
    "sourceUrl": "https://sportrbc.ru/news/69b316489a7947216ce53630",
    "publishedAt": "2026-03-12T19:59:49.000Z",
    "createdAt": "2026-03-13T07:02:31.091Z",
    "updatedAt": "2026-03-13T07:02:31.091Z"
  },
  {
    "id": "5bc1d4491fc28d4c",
    "title": "Боец ММА Шаблий сообщил о срыве поединка в Испании из-за отказа в визе",
    "sport": "Единоборства",
    "category": "Единоборства",
    "imageUrl": "https://s0.rbk.ru/v6_top_pics/media/img/4/54/347733399004544.jpeg",
    "teaser": "Боец ММА Шаблий сообщил о срыве поединка в Испании из-за отказа в визе",
    "fullContent": "",
    "sourceName": "РБК Спорт",
    "sourceUrl": "https://sportrbc.ru/news/69b302679a79472b8535e0d3",
    "publishedAt": "2026-03-12T18:55:34.000Z",
    "createdAt": "2026-03-13T07:02:33.265Z",
    "updatedAt": "2026-03-13T07:02:33.265Z"
  },
  {
    "id": "3cdd231483e4c474",
    "title": "Клебо увезли на скорой после падения и удара затылком во время гонки",
    "sport": "Другое",
    "category": "Другие",
    "imageUrl": "https://s0.rbk.ru/v6_top_pics/media/img/3/09/347733372785093.png",
    "teaser": "Клебо увезли на скорой после падения и удара затылком во время гонки",
    "fullContent": "",
    "sourceName": "РБК Спорт",
    "sourceUrl": "https://sportrbc.ru/news/69b2fa7d9a794704945305f7",
    "publishedAt": "2026-03-12T18:00:43.000Z",
    "createdAt": "2026-03-13T07:02:32.172Z",
    "updatedAt": "2026-03-13T07:02:32.172Z"
  },
  {
    "id": "65007bd33fb2f427",
    "title": "Умер единственный ирландский олимпийский чемпион в беге",
    "sport": "Другое",
    "category": "Другие",
    "imageUrl": "https://s0.rbk.ru/v6_top_pics/media/img/2/79/347733345996792.jpeg",
    "teaser": "Умер единственный ирландский олимпийский чемпион в беге",
    "fullContent": "",
    "sourceName": "РБК Спорт",
    "sourceUrl": "https://sportrbc.ru/news/69b2f01d9a79471c26f05d72",
    "publishedAt": "2026-03-12T17:25:08.000Z",
    "createdAt": "2026-03-13T07:02:34.354Z",
    "updatedAt": "2026-03-13T07:02:34.354Z"
  },
  {
    "id": "9469de675255aea2",
    "title": "Велогонщик попал под мотоцикл после падения на многодневке в Италии",
    "sport": "Другое",
    "category": "Другие",
    "imageUrl": "https://s0.rbk.ru/v6_top_pics/media/img/5/81/347733316451815.png",
    "teaser": "Велогонщик попал под мотоцикл после падения на многодневке в Италии",
    "fullContent": "",
    "sourceName": "РБК Спорт",
    "sourceUrl": "https://sportrbc.ru/news/69b2e4409a79477241325997",
    "publishedAt": "2026-03-12T17:06:59.000Z",
    "createdAt": "2026-03-13T07:02:36.613Z",
    "updatedAt": "2026-03-13T07:02:36.613Z"
  },
  {
    "id": "7f1016b19458d3e8",
    "title": "УЕФА открыл дело против форварда «Челси», толкнувшего бол-боя в матче ЛЧ",
    "sport": "Футбол",
    "category": "Футбол",
    "imageUrl": "https://s0.rbk.ru/v6_top_pics/media/img/7/08/347733334351087.jpeg",
    "teaser": "УЕФА открыл дело против форварда «Челси», толкнувшего бол-боя в матче ЛЧ",
    "fullContent": "",
    "sourceName": "РБК Спорт",
    "sourceUrl": "https://sportrbc.ru/news/69b2e68a9a7947c6a17057d7",
    "publishedAt": "2026-03-12T16:51:42.000Z",
    "createdAt": "2026-03-13T07:02:37.699Z",
    "updatedAt": "2026-03-13T07:02:37.699Z"
  },
  {
    "id": "1fe0154b497e2745",
    "title": "Трамп назвал неуместным приезд сборной Ирана на ЧМ-2026",
    "sport": "Футбол",
    "category": "Футбол",
    "imageUrl": "https://s0.rbk.ru/v6_top_pics/media/img/4/36/347733279228364.jpeg",
    "teaser": "Трамп назвал неуместным приезд сборной Ирана на ЧМ-2026",
    "fullContent": "",
    "sourceName": "РБК Спорт",
    "sourceUrl": "https://sportrbc.ru/news/69b2d5c49a7947e3f771ea39",
    "publishedAt": "2026-03-12T15:26:35.000Z",
    "createdAt": "2026-03-13T07:02:35.518Z",
    "updatedAt": "2026-03-13T07:02:35.518Z"
  }
]