[
  {
    "id": "31b8fe2b5b0e0593",
    "title": "Инфантино объяснил сильное повышение цен билетов на матчи ЧМ-2026",
    "sport": "Футбол",
    "category": "Футбол",
    "imageUrl": "https://s0.rbk.ru/v6_top_pics/media/img/1/10/347764307133101.jpeg",
    "teaser": "Инфантино объяснил сильное повышение цен билетов на матчи ЧМ-2026",
    "fullContent": "",
    "sourceName": "РБК Спорт",
    "sourceUrl": "https://sportrbc.ru/news/69e22e0a9a794724213e9183",
    "publishedAt": "2026-04-17T13:30:03.000Z",
    "createdAt": "2026-04-17T13:44:23.508Z",
    "updatedAt": "2026-04-17T13:44:23.508Z"
  },
  {
    "id": "b2df2f615214990c",
    "title": "Победителя турнира претендентов FIDE торжественно встретили в Узбекистане",
    "sport": "Другое",
    "category": "Другие",
    "imageUrl": "https://s0.rbk.ru/v6_top_pics/media/img/9/01/347764301506019.jpeg",
    "teaser": "Победителя турнира претендентов FIDE торжественно встретили в Узбекистане",
    "fullContent": "",
    "sourceName": "РБК Спорт",
    "sourceUrl": "https://sportrbc.ru/news/69e2281e9a79473293b3e71d",
    "publishedAt": "2026-04-17T13:11:29.000Z",
    "createdAt": "2026-04-17T13:44:24.499Z",
    "updatedAt": "2026-04-17T13:44:24.499Z"
  },
  {
    "id": "fcdd5a33c08224ac",
    "title": "Рублев четвертый раз в сезоне вышел в полуфинал на турнире ATP",
    "sport": "Теннис",
    "category": "Теннис",
    "imageUrl": "https://s0.rbk.ru/v6_top_pics/media/img/5/46/347764283024465.jpeg",
    "teaser": "Рублев четвертый раз в сезоне вышел в полуфинал на турнире ATP",
    "fullContent": "",
    "sourceName": "РБК Спорт",
    "sourceUrl": "https://sportrbc.ru/news/69e224d89a794761879273bb",
    "publishedAt": "2026-04-17T12:41:24.000Z",
    "createdAt": "2026-04-17T13:44:25.506Z",
    "updatedAt": "2026-04-17T13:44:25.506Z"
  },
  {
    "id": "430d6e8bbeb71666",
    "title": "РФС отменил красную карточку игрока «Зенита» в матче с «Краснодаром»",
    "sport": "Футбол",
    "category": "Футбол",
    "imageUrl": "https://s0.rbk.ru/v6_top_pics/media/img/7/48/347764283928487.jpeg",
    "teaser": "РФС отменил красную карточку игрока «Зенита» в матче с «Краснодаром»",
    "fullContent": "",
    "sourceName": "РБК Спорт",
    "sourceUrl": "https://sportrbc.ru/news/69e223219a7947f4652625b9",
    "publishedAt": "2026-04-17T12:23:09.000Z",
    "createdAt": "2026-04-17T13:44:26.630Z",
    "updatedAt": "2026-04-17T13:44:26.630Z"
  },
  {
    "id": "c99f655d58f74c24",
    "title": "РФС признал ошибочным назначение пенальти в ворота ЦСКА в матче с «Сочи»",
    "sport": "Футбол",
    "category": "Футбол",
    "imageUrl": "https://s0.rbk.ru/v6_top_pics/media/img/6/98/347764263553986.jpeg",
    "teaser": "РФС признал ошибочным назначение пенальти в ворота ЦСКА в матче с «Сочи»",
    "fullContent": "",
    "sourceName": "РБК Спорт",
    "sourceUrl": "https://sportrbc.ru/news/69e219b89a7947ac2c295d3c",
    "publishedAt": "2026-04-17T11:50:07.000Z",
    "createdAt": "2026-04-17T13:44:27.646Z",
    "updatedAt": "2026-04-17T13:44:27.646Z"
  },
  {
    "id": "ec97bbd3d13a9e2f",
    "title": "США пригрозили не пустить европейских чиновников на ЧМ-2026",
    "sport": "Футбол",
    "category": "Футбол",
    "imageUrl": "https://s0.rbk.ru/v6_top_pics/media/img/8/94/347764244696948.jpeg",
    "teaser": "США пригрозили не пустить европейских чиновников на ЧМ-2026",
    "fullContent": "",
    "sourceName": "РБК Спорт",
    "sourceUrl": "https://sportrbc.ru/news/69e2119b9a7947c09d466dc2",
    "publishedAt": "2026-04-17T11:32:57.000Z",
    "createdAt": "2026-04-17T13:44:28.642Z",
    "updatedAt": "2026-04-17T13:44:28.642Z"
  },
  {
    "id": "d031848acf649466",
    "title": "Глава РУСАДА оценила шансы выиграть дело у WADA в CAS",
    "sport": "Другое",
    "category": "Другие",
    "imageUrl": "https://s0.rbk.ru/v6_top_pics/media/img/7/26/347764236803267.jpeg",
    "teaser": "Глава РУСАДА оценила шансы выиграть дело у WADA в CAS",
    "fullContent": "",
    "sourceName": "РБК Спорт",
    "sourceUrl": "https://sportrbc.ru/news/69e212c69a79475461d59d50",
    "publishedAt": "2026-04-17T11:16:37.000Z",
    "createdAt": "2026-04-17T13:44:29.653Z",
    "updatedAt": "2026-04-17T13:44:29.653Z"
  },
  {
    "id": "1014c3b65629c379",
    "title": "Джокович снялся с третьего турнира серии «Мастерс» подряд",
    "sport": "Теннис",
    "category": "Теннис",
    "imageUrl": "https://s0.rbk.ru/v6_top_pics/media/img/0/41/347764227025410.jpeg",
    "teaser": "Джокович снялся с третьего турнира серии «Мастерс» подряд",
    "fullContent": "",
    "sourceName": "РБК Спорт",
    "sourceUrl": "https://sportrbc.ru/news/69e20aa89a7947f034b83523",
    "publishedAt": "2026-04-17T10:57:44.000Z",
    "createdAt": "2026-04-17T13:44:30.684Z",
    "updatedAt": "2026-04-17T13:44:30.684Z"
  },
  {
    "id": "000e471fde9bc94c",
    "title": "Свищев пообещал, что Губерниев и Вяльбе сработаются в лыжных гонках",
    "sport": "Другое",
    "category": "Другие",
    "imageUrl": "https://s0.rbk.ru/v6_top_pics/media/img/7/44/347764208708447.jpeg",
    "teaser": "Свищев пообещал, что Губерниев и Вяльбе сработаются в лыжных гонках",
    "fullContent": "",
    "sourceName": "РБК Спорт",
    "sourceUrl": "https://sportrbc.ru/news/69e201f19a7947060522e731",
    "publishedAt": "2026-04-17T10:57:04.000Z",
    "createdAt": "2026-04-17T13:44:31.681Z",
    "updatedAt": "2026-04-17T13:44:31.681Z"
  },
  {
    "id": "2b52ec69d9cf8026",
    "title": "У Российской премьер-лиги сменился титульный спонсор",
    "sport": "Футбол",
    "category": "Футбол",
    "imageUrl": "https://s0.rbk.ru/v6_top_pics/media/img/8/17/347764131155178.jpeg",
    "teaser": "У Российской премьер-лиги сменился титульный спонсор",
    "fullContent": "",
    "sourceName": "РБК Спорт",
    "sourceUrl": "https://sportrbc.ru/news/69e1e9299a7947ae2bd161ec",
    "publishedAt": "2026-04-17T09:49:54.000Z",
    "createdAt": "2026-04-17T13:44:32.681Z",
    "updatedAt": "2026-04-17T13:44:32.682Z"
  }
]