[
  {
    "id": "1a04af4117d92b34",
    "title": "Умер экс-глава WADA, запустивший расследования о допинге в России",
    "sport": "Другое",
    "category": "Другие",
    "imageUrl": "https://s0.rbk.ru/v6_top_pics/media/img/3/82/347754923423823.png",
    "teaser": "Умер экс-глава WADA, запустивший расследования о допинге в России",
    "fullContent": "",
    "sourceName": "РБК Спорт",
    "sourceUrl": "https://sportrbc.ru/news/69d3dbdf9a7947bd894119a2",
    "publishedAt": "2026-04-06T16:46:19.000Z",
    "createdAt": "2026-04-06T16:56:49.633Z",
    "updatedAt": "2026-04-06T16:56:49.633Z"
  },
  {
    "id": "b4f9487532119215",
    "title": "В США сделали скульптуру Овечкина из зефира",
    "sport": "Хоккей",
    "category": "Хоккей",
    "imageUrl": "https://s0.rbk.ru/v6_top_pics/media/img/1/08/347754923101081.jpeg",
    "teaser": "В США сделали скульптуру Овечкина из зефира",
    "fullContent": "",
    "sourceName": "РБК Спорт",
    "sourceUrl": "https://sportrbc.ru/news/69d3d9fe9a79470973c3eb96",
    "publishedAt": "2026-04-06T16:43:48.000Z",
    "createdAt": "2026-04-06T16:56:50.929Z",
    "updatedAt": "2026-04-06T16:56:50.929Z"
  },
  {
    "id": "033ea8c0a2eb6529",
    "title": "Смолов заявил, что пропавшие в Казани часы «переплавились» в золото РПЛ",
    "sport": "Футбол",
    "category": "Футбол",
    "imageUrl": "https://s0.rbk.ru/v6_top_pics/media/img/0/25/347754890158250.jpeg",
    "teaser": "Смолов заявил, что пропавшие в Казани часы «переплавились» в золото РПЛ",
    "fullContent": "",
    "sourceName": "РБК Спорт",
    "sourceUrl": "https://sportrbc.ru/news/69d3cb289a794731080aba5b",
    "publishedAt": "2026-04-06T15:43:57.000Z",
    "createdAt": "2026-04-06T16:56:51.888Z",
    "updatedAt": "2026-04-06T16:56:51.888Z"
  },
  {
    "id": "3d5a2f3d21587d5a",
    "title": "Тренера «Динамо» пригласили на заседание КДК после 12 матерных реплик",
    "sport": "Футбол",
    "category": "Футбол",
    "imageUrl": "https://s0.rbk.ru/v6_top_pics/media/img/9/93/347754867195939.jpeg",
    "teaser": "Тренера «Динамо» пригласили на заседание КДК после 12 матерных реплик",
    "fullContent": "",
    "sourceName": "РБК Спорт",
    "sourceUrl": "https://sportrbc.ru/news/69d3c3229a79478c79107fde",
    "publishedAt": "2026-04-06T14:51:13.000Z",
    "createdAt": "2026-04-06T16:56:52.891Z",
    "updatedAt": "2026-04-06T16:56:52.891Z"
  },
  {
    "id": "32b24d7fa83a65e2",
    "title": "Российский биатлонист объяснил уход в лыжные гонки",
    "sport": "Другое",
    "category": "Биатлон",
    "imageUrl": "https://s0.rbk.ru/v6_top_pics/media/img/7/16/347754856887167.jpeg",
    "teaser": "Российский биатлонист объяснил уход в лыжные гонки",
    "fullContent": "",
    "sourceName": "РБК Спорт",
    "sourceUrl": "https://sportrbc.ru/news/69d3be3a9a79477734ee4fa2",
    "publishedAt": "2026-04-06T14:49:36.000Z",
    "createdAt": "2026-04-06T16:56:55.862Z",
    "updatedAt": "2026-04-06T16:56:55.862Z"
  },
  {
    "id": "b5f07420a815f6fa",
    "title": "Болельщик умер во время футбольного матча Первой лиги в Туле",
    "sport": "Футбол",
    "category": "Футбол",
    "imageUrl": "/images/news-placeholder.jpg",
    "teaser": "Болельщик умер во время футбольного матча Первой лиги в Туле",
    "fullContent": "",
    "sourceName": "РБК Спорт",
    "sourceUrl": "https://sportrbc.ru/news/69d3bd759a79472937f02bb4",
    "publishedAt": "2026-04-06T14:32:25.000Z",
    "createdAt": "2026-04-06T16:56:54.780Z",
    "updatedAt": "2026-04-06T16:56:54.780Z"
  },
  {
    "id": "89ab24106d555400",
    "title": "Ла Лига подаст жалобу на фанатов «Севильи» за пожелания смерти команде",
    "sport": "Футбол",
    "category": "Футбол",
    "imageUrl": "https://s0.rbk.ru/v6_top_pics/media/img/0/46/347754833482460.jpeg",
    "teaser": "Ла Лига подаст жалобу на фанатов «Севильи» за пожелания смерти команде",
    "fullContent": "",
    "sourceName": "РБК Спорт",
    "sourceUrl": "https://sportrbc.ru/news/69d3b5439a794752e36ca7c2",
    "publishedAt": "2026-04-06T14:15:41.000Z",
    "createdAt": "2026-04-06T16:56:56.919Z",
    "updatedAt": "2026-04-06T16:56:56.919Z"
  },
  {
    "id": "25166db4caf1d3e8",
    "title": "«Авангард» продлил контракт с одним из лидеров",
    "sport": "Хоккей",
    "category": "Хоккей",
    "imageUrl": "https://s0.rbk.ru/v6_top_pics/media/img/4/56/347754839747564.jpeg",
    "teaser": "«Авангард» продлил контракт с одним из лидеров",
    "fullContent": "",
    "sourceName": "РБК Спорт",
    "sourceUrl": "https://sportrbc.ru/news/69d3b9599a79475daf3dada8",
    "publishedAt": "2026-04-06T14:11:54.000Z",
    "createdAt": "2026-04-06T16:56:59.111Z",
    "updatedAt": "2026-04-06T16:56:59.111Z"
  },
  {
    "id": "d5456001da4b1f74",
    "title": "Фанаты «Зенита» отказались от мата в адрес «Спартака» в Страстную неделю",
    "sport": "Футбол",
    "category": "Футбол",
    "imageUrl": "https://s0.rbk.ru/v6_top_pics/media/img/9/56/347754824131569.jpeg",
    "teaser": "Фанаты «Зенита» отказались от мата в адрес «Спартака» в Страстную неделю",
    "fullContent": "",
    "sourceName": "РБК Спорт",
    "sourceUrl": "https://sportrbc.ru/news/69d3ae3c9a79470346af09ec",
    "publishedAt": "2026-04-06T13:48:59.000Z",
    "createdAt": "2026-04-06T16:56:58.030Z",
    "updatedAt": "2026-04-06T16:56:58.030Z"
  },
  {
    "id": "30c85053edb43450",
    "title": "Рублев рассказал о победе на «лошадиной» дозе обезболивающих",
    "sport": "Теннис",
    "category": "Теннис",
    "imageUrl": "https://s0.rbk.ru/v6_top_pics/media/img/3/49/347754808906493.jpeg",
    "teaser": "Рублев рассказал о победе на «лошадиной» дозе обезболивающих",
    "fullContent": "",
    "sourceName": "РБК Спорт",
    "sourceUrl": "https://sportrbc.ru/news/69d3a94a9a79472f96766752",
    "publishedAt": "2026-04-06T13:16:40.000Z",
    "createdAt": "2026-04-06T16:57:00.180Z",
    "updatedAt": "2026-04-06T16:57:00.180Z"
  }
]