[
  {
    "id": "b4c7b8fffcd731c5",
    "title": "В Бразилии случайно застрелили 22-летнего экс-игрока «Крузейро»",
    "sport": "Футбол",
    "category": "Футбол",
    "imageUrl": "/images/news-placeholder.jpg",
    "teaser": "В Бразилии случайно застрелили 22-летнего экс-игрока «Крузейро»",
    "fullContent": "",
    "sourceName": "РБК Спорт",
    "sourceUrl": "https://sportrbc.ru/news/6983532f9a7947e1e2f727ec",
    "publishedAt": "2026-02-04T14:22:26.000Z",
    "createdAt": "2026-02-04T14:46:57.251Z",
    "updatedAt": "2026-02-04T14:46:57.251Z"
  },
  {
    "id": "da7f204616a9006a",
    "title": "Норвежского горнолыжника эвакуировали с олимпийской трассы на вертолете",
    "sport": "Другое",
    "category": "Другие",
    "imageUrl": "https://s0.rbk.ru/v6_top_pics/media/img/7/79/347702103528797.jpeg",
    "teaser": "Норвежского горнолыжника эвакуировали с олимпийской трассы на вертолете",
    "fullContent": "",
    "sourceName": "РБК Спорт",
    "sourceUrl": "https://sportrbc.ru/news/69833f769a79474c858c5a19",
    "publishedAt": "2026-02-04T13:48:54.000Z",
    "createdAt": "2026-02-04T14:46:59.324Z",
    "updatedAt": "2026-02-04T14:46:59.324Z"
  },
  {
    "id": "7b1872e6346b14f1",
    "title": "Умер бывший тренер сборных СССР и России Владимир Камельзон",
    "sport": "Теннис",
    "category": "Теннис",
    "imageUrl": "https://s0.rbk.ru/v6_top_pics/media/img/1/73/347702101063731.jpeg",
    "teaser": "Умер бывший тренер сборных СССР и России Владимир Камельзон",
    "fullContent": "",
    "sourceName": "РБК Спорт",
    "sourceUrl": "https://sportrbc.ru/news/698341c79a7947099294943e",
    "publishedAt": "2026-02-04T13:36:59.000Z",
    "createdAt": "2026-02-04T14:46:55.356Z",
    "updatedAt": "2026-02-04T14:46:55.356Z"
  },
  {
    "id": "ad554e9c99931e75",
    "title": "Финские хоккеистки заразились норовирусом перед матчем с Канадой на Играх",
    "sport": "Хоккей",
    "category": "Хоккей",
    "imageUrl": "https://s0.rbk.ru/v6_top_pics/media/img/1/19/347702099406191.png",
    "teaser": "Финские хоккеистки заразились норовирусом перед матчем с Канадой на Играх",
    "fullContent": "",
    "sourceName": "РБК Спорт",
    "sourceUrl": "https://sportrbc.ru/news/69833f9d9a79477710091507",
    "publishedAt": "2026-02-04T13:27:02.000Z",
    "createdAt": "2026-02-04T14:47:02.459Z",
    "updatedAt": "2026-02-04T14:47:02.459Z"
  },
  {
    "id": "6cf79ce9dc86ba27",
    "title": "Сменившая гражданство Потапова выбила россиянку с турнира в Румынии",
    "sport": "Теннис",
    "category": "Теннис",
    "imageUrl": "https://s0.rbk.ru/v6_top_pics/media/img/9/57/347702062978579.png",
    "teaser": "Сменившая гражданство Потапова выбила россиянку с турнира в Румынии",
    "fullContent": "",
    "sourceName": "РБК Спорт",
    "sourceUrl": "https://sportrbc.ru/news/698334029a7947a6dc880084",
    "publishedAt": "2026-02-04T13:11:35.000Z",
    "createdAt": "2026-02-04T14:47:00.427Z",
    "updatedAt": "2026-02-04T14:47:00.427Z"
  },
  {
    "id": "8a8eef4cada4d45d",
    "title": "Сына экс-главы МОК Самаранча снова избрали вице-президентом организации",
    "sport": "Другое",
    "category": "Другие",
    "imageUrl": "https://s0.rbk.ru/v6_top_pics/media/img/0/29/347702054268290.jpeg",
    "teaser": "Сына экс-главы МОК Самаранча снова избрали вице-президентом организации",
    "fullContent": "",
    "sourceName": "РБК Спорт",
    "sourceUrl": "https://sportrbc.ru/news/69832d899a7947d8002178cf",
    "publishedAt": "2026-02-04T12:47:46.000Z",
    "createdAt": "2026-02-04T14:47:01.481Z",
    "updatedAt": "2026-02-04T14:47:01.481Z"
  },
  {
    "id": "4937c56883e4592b",
    "title": "Снуп Догг принял участие в эстафете олимпийского огня",
    "sport": "Другое",
    "category": "Другие",
    "imageUrl": "https://s0.rbk.ru/v6_top_pics/media/img/2/72/347702080182722.jpeg",
    "teaser": "Снуп Догг принял участие в эстафете олимпийского огня",
    "fullContent": "",
    "sourceName": "РБК Спорт",
    "sourceUrl": "https://sportrbc.ru/news/698337a09a79471eebef26ad",
    "publishedAt": "2026-02-04T12:38:35.000Z",
    "createdAt": "2026-02-04T14:46:58.226Z",
    "updatedAt": "2026-02-04T14:46:58.226Z"
  },
  {
    "id": "b93edd5a5faca168",
    "title": "Тутберидзе рассказала о проблемах Петросян со здоровьем за месяц до Игр",
    "sport": "Другое",
    "category": "Фигурное катание",
    "imageUrl": "https://s0.rbk.ru/v6_top_pics/media/img/4/97/347702043605974.png",
    "teaser": "Тутберидзе рассказала о проблемах Петросян со здоровьем за месяц до Игр",
    "fullContent": "",
    "sourceName": "РБК Спорт",
    "sourceUrl": "https://sportrbc.ru/news/69831fb99a79471a4be8b557",
    "publishedAt": "2026-02-04T11:46:57.000Z",
    "createdAt": "2026-02-04T14:47:03.551Z",
    "updatedAt": "2026-02-04T14:47:03.551Z"
  },
  {
    "id": "41cdd445f180a4db",
    "title": "Петросян фразой «была совсем без ноги» рассказала об отборе на Игры",
    "sport": "Другое",
    "category": "Фигурное катание",
    "imageUrl": "https://s0.rbk.ru/v6_top_pics/media/img/9/74/347702035593749.jpeg",
    "teaser": "Петросян фразой «была совсем без ноги» рассказала об отборе на Игры",
    "fullContent": "",
    "sourceName": "РБК Спорт",
    "sourceUrl": "https://sportrbc.ru/news/6983271a9a7947e412faa94d",
    "publishedAt": "2026-02-04T11:44:51.000Z",
    "createdAt": "2026-02-04T14:47:04.629Z",
    "updatedAt": "2026-02-04T14:47:04.629Z"
  },
  {
    "id": "6d1980825209311b",
    "title": "Тутберидзе рассказала, как Петросян поборется за медаль Олимпиады",
    "sport": "Другое",
    "category": "Фигурное катание",
    "imageUrl": "https://s0.rbk.ru/v6_top_pics/media/img/0/77/347702012589770.png",
    "teaser": "Тутберидзе рассказала, как Петросян поборется за медаль Олимпиады",
    "fullContent": "",
    "sourceName": "РБК Спорт",
    "sourceUrl": "https://sportrbc.ru/news/69831d449a7947a1f2616b6e",
    "publishedAt": "2026-02-04T11:16:19.000Z",
    "createdAt": "2026-02-04T14:47:05.716Z",
    "updatedAt": "2026-02-04T14:47:05.716Z"
  }
]